cfgnlog/Configure.py
cfgnlog/Log.py
cfgnlog/__init__.py
cfgnlog_YmirSystems-0.0.2.dist-info/LICENSE
cfgnlog_YmirSystems-0.0.2.dist-info/METADATA
cfgnlog_YmirSystems-0.0.2.dist-info/WHEEL
cfgnlog_YmirSystems-0.0.2.dist-info/top_level.txt
cfgnlog_YmirSystems-0.0.2.dist-info/RECORD
