Metadata-Version: 2.1
Name: cfgnlog-YmirSystems
Version: 0.0.2
Summary: Simple configuration and log files. Config files use JSON. XDG compliant by default.
Home-page: https://github.com/YmirSystems/cfgnlog
Author: Ymir Systems
Author-email: info@YmirSystems.com
License: UNKNOWN
Platform: UNKNOWN
Classifier: Development Status :: 3 - Alpha
Classifier: Intended Audience :: Developers
Classifier: Operating System :: OS Independent
Classifier: License :: OSI Approved :: Artistic License
Classifier: Programming Language :: Python :: 2.7
Classifier: Programming Language :: Python :: 3
